{"ppg":[{"name":"Joe Fulks","team":"PHW","pos":"PF","gp":"60","mpg":"","stat":"23.2","fg_pct":".305","fg3_pct":"","ft_pct":".730","trb":"","ast":"0.4","stl":"","blk":""},{"name":"Bob Feerick","team":"WSC","pos":"","gp":"55","mpg":"","stat":"16.8","fg_pct":".401","fg3_pct":"","ft_pct":".762","trb":"","ast":"1.3","stl":"","blk":""},{"name":"Ed Sadowski","team":"2TM","pos":"","gp":"53","mpg":"","stat":"16.5","fg_pct":".369","fg3_pct":"","ft_pct":".668","trb":"","ast":"0.9","stl":"","blk":""},{"name":"Stan Miasek","team":"DTF","pos":"","gp":"60","mpg":"","stat":"14.9","fg_pct":".287","fg3_pct":"","ft_pct":".605","trb":"","ast":"1.6","stl":"","blk":""},{"name":"Max Zaslofsky","team":"CHS","pos":"SG","gp":"61","mpg":"","stat":"14.4","fg_pct":".329","fg3_pct":"","ft_pct":".737","trb":"","ast":"0.7","stl":"","blk":""},{"name":"Ernie Calverley","team":"PRO","pos":"","gp":"59","mpg":"","stat":"14.3","fg_pct":".293","fg3_pct":"","ft_pct":".703","trb":"","ast":"3.4","stl":"","blk":""},{"name":"Coulby Gunther","team":"PIT","pos":"","gp":"52","mpg":"","stat":"14.1","fg_pct":".336","fg3_pct":"","ft_pct":".644","trb":"","ast":"0.6","stl":"","blk":""},{"name":"Frankie Baumholtz","team":"CLR","pos":"","gp":"45","mpg":"","stat":"14.0","fg_pct":".298","fg3_pct":"","ft_pct":".776","trb":"","ast":"1.2","stl":"","blk":""},{"name":"Leo Mogus","team":"2TM","pos":"","gp":"58","mpg":"","stat":"13.0","fg_pct":".295","fg3_pct":"","ft_pct":".723","trb":"","ast":"1.4","stl":"","blk":""},{"name":"Chick Halbert","team":"CHS","pos":"","gp":"61","mpg":"","stat":"12.7","fg_pct":".306","fg3_pct":"","ft_pct":".598","trb":"","ast":"0.8","stl":"","blk":""},{"name":"John Logan","team":"STB","pos":"","gp":"61","mpg":"","stat":"12.6","fg_pct":".278","fg3_pct":"","ft_pct":".748","trb":"","ast":"1.3","stl":"","blk":""},{"name":"Fred Scolari","team":"WSC","pos":"PG","gp":"58","mpg":"","stat":"12.6","fg_pct":".294","fg3_pct":"","ft_pct":".811","trb":"","ast":"1.0","stl":"","blk":""},{"name":"Hank Beenders","team":"PRO","pos":"","gp":"58","mpg":"","stat":"12.3","fg_pct":".262","fg3_pct":"","ft_pct":".704","trb":"","ast":"0.6","stl":"","blk":""},{"name":"Dino Martin","team":"PRO","pos":"","gp":"60","mpg":"","stat":"12.2","fg_pct":".304","fg3_pct":"","ft_pct":".661","trb":"","ast":"1.0","stl":"","blk":""},{"name":"Mel Riebe","team":"CLR","pos":"","gp":"55","mpg":"","stat":"12.1","fg_pct":".307","fg3_pct":"","ft_pct":".642","trb":"","ast":"1.2","stl":"","blk":""}],"apg":[{"name":"Ernie Calverley","team":"PRO","pos":"","gp":"59","mpg":"","stat":"3.4","fg_pct":".293","fg3_pct":"","ft_pct":".703","trb":"","ast":"3.4","stl":"","blk":""},{"name":"Kenny Sailors","team":"CLR","pos":"","gp":"58","mpg":"","stat":"2.3","fg_pct":".309","fg3_pct":"","ft_pct":".595","trb":"","ast":"2.3","stl":"","blk":""},{"name":"Ossie Schectman","team":"NYK","pos":"","gp":"54","mpg":"","stat":"2.0","fg_pct":".276","fg3_pct":"","ft_pct":".620","trb":"","ast":"2.0","stl":"","blk":""},{"name":"Howie Dallmar","team":"PHW","pos":"","gp":"60","mpg":"","stat":"1.7","fg_pct":".280","fg3_pct":"","ft_pct":".640","trb":"","ast":"1.7","stl":"","blk":""},{"name":"Mickey Rottner","team":"CHS","pos":"","gp":"56","mpg":"","stat":"1.7","fg_pct":".290","fg3_pct":"","ft_pct":".544","trb":"","ast":"1.7","stl":"","blk":""},{"name":"Art Stolkey","team":"DTF","pos":"","gp":"23","mpg":"","stat":"1.7","fg_pct":".220","fg3_pct":"","ft_pct":".682","trb":"","ast":"1.7","stl":"","blk":""},{"name":"Stan Miasek","team":"DTF","pos":"","gp":"60","mpg":"","stat":"1.6","fg_pct":".287","fg3_pct":"","ft_pct":".605","trb":"","ast":"1.6","stl":"","blk":""},{"name":"Earl Shannon","team":"PRO","pos":"","gp":"57","mpg":"","stat":"1.5","fg_pct":".339","fg3_pct":"","ft_pct":".566","trb":"","ast":"1.5","stl":"","blk":""},{"name":"Jack Garfinkel","team":"BOS","pos":"","gp":"40","mpg":"","stat":"1.5","fg_pct":".266","fg3_pct":"","ft_pct":".607","trb":"","ast":"1.5","stl":"","blk":""},{"name":"Leo Mogus","team":"2TM","pos":"","gp":"58","mpg":"","stat":"1.4","fg_pct":".295","fg3_pct":"","ft_pct":".723","trb":"","ast":"1.4","stl":"","blk":""},{"name":"Bob Feerick","team":"WSC","pos":"","gp":"55","mpg":"","stat":"1.3","fg_pct":".401","fg3_pct":"","ft_pct":".762","trb":"","ast":"1.3","stl":"","blk":""},{"name":"John Logan","team":"STB","pos":"","gp":"61","mpg":"","stat":"1.3","fg_pct":".278","fg3_pct":"","ft_pct":".748","trb":"","ast":"1.3","stl":"","blk":""},{"name":"Frankie Baumholtz","team":"CLR","pos":"","gp":"45","mpg":"","stat":"1.2","fg_pct":".298","fg3_pct":"","ft_pct":".776","trb":"","ast":"1.2","stl":"","blk":""},{"name":"Mel Riebe","team":"CLR","pos":"","gp":"55","mpg":"","stat":"1.2","fg_pct":".307","fg3_pct":"","ft_pct":".642","trb":"","ast":"1.2","stl":"","blk":""},{"name":"Bones McKinney","team":"WSC","pos":"SF","gp":"58","mpg":"","stat":"1.2","fg_pct":".279","fg3_pct":"","ft_pct":".690","trb":"","ast":"1.2","stl":"","blk":""}],"rpg":[]}